lab_notebook-3.3.3.data/scripts/runs-git
lab_notebook-3.3.3.dist-info/METADATA
lab_notebook-3.3.3.dist-info/RECORD
lab_notebook-3.3.3.dist-info/WHEEL
lab_notebook-3.3.3.dist-info/entry_points.txt
lab_notebook-3.3.3.dist-info/top_level.txt
runs/__init__.py
runs/convert_to_db.py
runs/database.py
runs/file_system.py
runs/logger.py
runs/main.py
runs/query.py
runs/run_entry.py
runs/shell.py
runs/tensorflow_util.py
runs/tests.py
runs/tmux_session.py
runs/util.py
runs/commands/__init__.py
runs/commands/change_description.py
runs/commands/correlate.py
runs/commands/flags.py
runs/commands/kill.py
runs/commands/lookup.py
runs/commands/ls.py
runs/commands/mv.py
runs/commands/new.py
runs/commands/new_from_spec.py
runs/commands/reproduce.py
runs/commands/rm.py
runs/commands/table.py
runs/transaction/__init__.py
runs/transaction/change_description.py
runs/transaction/kill.py
runs/transaction/move.py
runs/transaction/new.py
runs/transaction/removal.py
runs/transaction/sub_transaction.py
runs/transaction/transaction.py
