Metadata-Version: 2.1
Name: lab-notebook
Version: 3.3.3
Summary: A utility for tracking, documenting, and reproducing software runs.
Home-page: https://github.com/lobachevzky/lab-notebook
Author: Ethan Brooks
Author-email: ethanbrooks@gmail.com
License: MIT
Keywords: tensorflow utilities development
Platform: UNKNOWN
Classifier: Development Status :: 3 - Alpha
Classifier: Intended Audience :: Developers
Classifier: Topic :: Scientific/Engineering :: Artificial Intelligence
Classifier: License :: OSI Approved :: MIT License
Classifier: Programming Language :: Python :: 3.7
